zensus2pgsql/__init__.py
zensus2pgsql/cache.py
zensus2pgsql/cli.py
zensus2pgsql/constants.py
zensus2pgsql/errors.py
zensus2pgsql/logging.py
zensus2pgsql/retry.py
zensus2pgsql/commands/__init__.py
zensus2pgsql/commands/_base.py
zensus2pgsql/commands/cache.py
zensus2pgsql/commands/create.py
zensus2pgsql/commands/drop.py
zensus2pgsql/commands/list.py
zensus2pgsql-0.2.1.dist-info/METADATA
zensus2pgsql-0.2.1.dist-info/WHEEL
zensus2pgsql-0.2.1.dist-info/entry_points.txt
zensus2pgsql-0.2.1.dist-info/licenses/COPYING
zensus2pgsql-0.2.1.dist-info/RECORD
