Metadata-Version: 2.4
Name: zensus2pgsql
Version: 0.2.1
Summary: A Python CLI program that collects Zensus GIS data from Germany and imports it into PostgreSQL
Project-URL: homepage, https://github.com/travishathaway/zensus2pgsql
Project-URL: source, https://github.com/travishathaway/zensus2pgsql
Project-URL: changelog, https://github.com/travishathaway/zensus2pgsql/blob/main/CHANGELOG.md
Project-URL: releasenotes, https://github.com/travishathaway/zensus2pgsql/releases
Project-URL: documentation, https://travishathaway.github.io/zensus2pgsql
Project-URL: issues, https://github.com/travishathaway/zensus2pgsql/issues
Author-email: Travis Hathaway <travis.j.hathaway@gmail.com>
License-File: COPYING
Requires-Python: <4.0,>=3.10
Requires-Dist: aiocsv>=1.4.0
Requires-Dist: aiofiles>=25.1.0
Requires-Dist: asyncpg>=0.30.0
Requires-Dist: httpx>=0.28.1
Requires-Dist: platformdirs>=4.5.0
Requires-Dist: rich>=14.2.0
Requires-Dist: typer>=0.15.1
Requires-Dist: types-aiofiles>=25.1.0.20251011
